<?xml version="1.0" encoding="UTF-8"?>
<!-- Foundation -->
<window id="104">
    <zorder>10</zorder>
    <controls>

        <!-- Mute bug for OSD -->
        <control type="group">
            <visible>[VideoPlayer.IsFullscreen | Window.IsVisible(MusicVisualisation.xml)]</visible>
            <visible>Player.Muted</visible>
            <visible>![Player.ShowInfo | Window.IsVisible(script-cu-lrclyrics-main.xml) | !String.IsEmpty(Window(Home).Property(OSDInfo)) | Player.ShowInfo | Window.IsActive(DialogFullScreenInfo.xml) | [Player.Paused + Skin.HasSetting(ShowInfoPaused)]]</visible>
            <include>Animation_FadeIn_Slide</include>
            <control type="image">
                <width>216</width>
                <height>216</height>
                <left>2</left>
                <top>-10</top>
                <texture>common/shadowspot.png</texture>
            </control>
            <control type="image">
                <left>70</left>
                <top>58</top>
                <width>80</width>
                <height>80</height>
                <texture colordiffuse="main_fg_100">buttons/mute.png</texture>
            </control>
        </control>
        <control type="image">
            <include>Defs_ShadowBack_Fullscreen</include>
            <visible>!Player.Muted</visible>
        </control>
        <control type="group">
            <include>Animation_FadeIn_Slide</include>
            <visible>!Player.Muted</visible>
            <!-- Volume bar -->
            <control type="group">
                <height>view_top</height>
                <control type="grouplist">
                    <right>view_pad</right>
                    <height>100%</height>
                    <align>right</align>
                    <orientation>horizontal</orientation>
                    <itemgap>0</itemgap>
                    <usecontrolcoords>true</usecontrolcoords>
                    <control type="image">
                        <centertop>50%</centertop>
                        <height>64</height>
                        <width>64</width>
                        <texture colordiffuse="main_fg_100">special://skin/extras/icons/volume.png</texture>
                    </control>
                    <control type="label">
                        <height>100%</height>
                        <align>right</align>
                        <font>font_small</font>
                        <aligny>center</aligny>
                        <width>148</width>
                        <textcolor>main_fg_100</textcolor>
                        <label>$INFO[Player.Volume,  ,    ]</label>
                    </control>
                    <control type="group">
                        <centertop>50%</centertop>
                        <width>200</width>
                        <height>16</height>
                        <control type="progress">
                            <width>200</width>
                            <height>16</height>
                            <info>Player.Volume</info>
                            <texturebg colordiffuse="main_fg_12">progress/back-small.png</texturebg>
                            <lefttexture colordiffuse="$VAR[ColorHighlight2]">progress/left.png</lefttexture>
                            <midtexture colordiffuse="$VAR[ColorHighlight2]">progress/mid-small.png</midtexture>
                            <righttexture colordiffuse="$VAR[ColorHighlight2]">progress/right.png</righttexture>
                        </control>
                        <control type="progress">
                            <width>200</width>
                            <height>16</height>
                            <info>Player.Volume</info>
                            <texturebg colordiffuse="00ffffff">progress/back-small.png</texturebg>
                            <lefttexture colordiffuse="$VAR[ColorHighlight]">progress/left.png</lefttexture>
                            <midtexture colordiffuse="$VAR[ColorHighlight]">progress/mid-small.png</midtexture>
                            <righttexture colordiffuse="$VAR[ColorHighlight]">progress/right.png</righttexture>
                            <include content="Defs_Progress_Colorfade">
                                <param name="id" value="1" />
                            </include>
                        </control>
                    </control>
                    <control type="label">
                        <height>100%</height>
                        <align>right</align>
                        <font>font_small</font>
                        <aligny>center</aligny>
                        <width>80</width>
                        <textcolor>main_fg_100</textcolor>
                        <label>$INFO[Control.GetLabel(1),,%]</label>
                    </control>
                </control>
            </control>
        </control>

        <control type="progress" id="1">
            <description>progress control</description>
            <left>104</left>
            <right>24</right>
            <bottom>24</bottom>
            <height>8</height>
            <texturebg colordiffuse="dialog_bg_12">osd/progress-bg.png</texturebg>
            <info>Player.Volume</info>
            <visible>false</visible>
        </control>

    </controls>

</window>
